ghs/__init__.py
ghs/check_config.py
ghs/es_queries.py
ghs/fetchers.py
ghs/ghs.py
ghs/utils.py
ghs/viewer.py
ghs-0.1.4.dist-info/LICENSE
ghs-0.1.4.dist-info/METADATA
ghs-0.1.4.dist-info/WHEEL
ghs-0.1.4.dist-info/entry_points.txt
ghs-0.1.4.dist-info/top_level.txt
ghs-0.1.4.dist-info/RECORD
