Metadata-Version: 2.1
Name: ghs
Version: 0.1.4
Summary: Get you Github profile's stats and summary.
Home-page: http://github.com/interviewstreet/ghs
Author: Hackerrank
Author-email: pypi@hackerrank.com
License: MIT
Keywords: github,cli,utility,command,console
Classifier: Environment :: Console
Classifier: Intended Audience :: Developers
Classifier: License :: OSI Approved :: MIT License
Classifier: Natural Language :: English
Classifier: Operating System :: OS Independent
Classifier: Programming Language :: Python :: 3
Classifier: Topic :: Utilities
License-File: LICENSE
Requires-Dist: requests
Requires-Dist: retry-requests
Requires-Dist: python-dateutil
Requires-Dist: termcolor
Requires-Dist: colorama
Requires-Dist: pyperclip
Requires-Dist: halo
